pwntools_dbg_r2-0.1.6.data/scripts/pwntools-gdb
pwntools_dbg_r2-0.1.6.data/scripts/r2-session
pwntools_dbg_r2-0.1.6.data/scripts/radare2session
r2dbg/__init__.py
pwntools_dbg_r2-0.1.6.dist-info/LICENSE
pwntools_dbg_r2-0.1.6.dist-info/METADATA
pwntools_dbg_r2-0.1.6.dist-info/WHEEL
pwntools_dbg_r2-0.1.6.dist-info/top_level.txt
pwntools_dbg_r2-0.1.6.dist-info/RECORD
