Metadata-Version: 2.1
Name: pwntools-dbg-r2
Version: 0.1.6
Summary: Package to enable debugging with Radare2 in pwntools
Home-page: https://github.com/Enigmatrix/pwntools-dbg-r2
Author: Enigmatrix
Author-email: enigmatrix2000@gmail.com
License: UNKNOWN
Platform: UNKNOWN
Classifier: Programming Language :: Python :: 2
Classifier: License :: OSI Approved :: MIT License
Classifier: Operating System :: OS Independent
